salt_sproxy-2023.8.0-py3.9-nspkg.pth
salt_sproxy/cli.py
salt_sproxy/parsers.py
salt_sproxy/scripts.py
salt_sproxy/version.py
salt_sproxy/_executors/ssh.py
salt_sproxy/_modules/netbox.py
salt_sproxy/_proxy/ssh.py
salt_sproxy/_roster/__init__.py
salt_sproxy/_roster/ansible.py
salt_sproxy/_roster/file.py
salt_sproxy/_roster/netbox.py
salt_sproxy/_roster/pillar.py
salt_sproxy/_runners/__init__.py
salt_sproxy/_runners/proxy.py
salt_sproxy-2023.8.0.data/data/man/man1/salt-sapi.1
salt_sproxy-2023.8.0.data/data/man/man1/salt-sproxy.1
salt_sproxy-2023.8.0.dist-info/LICENSE
salt_sproxy-2023.8.0.dist-info/METADATA
salt_sproxy-2023.8.0.dist-info/WHEEL
salt_sproxy-2023.8.0.dist-info/entry_points.txt
salt_sproxy-2023.8.0.dist-info/namespace_packages.txt
salt_sproxy-2023.8.0.dist-info/top_level.txt
salt_sproxy-2023.8.0.dist-info/RECORD
