Metadata-Version: 2.1
Name: salt-sproxy
Version: 2023.8.0
Summary: Salt plugin for managing devices and applications, without running (Proxy) Minions
Home-page: https://github.com/mirceaulinic/salt-sproxy
Author: Mircea Ulinic
Author-email: ping@mirceaulinic.net
License: Apache License 2.0
Project-URL: CI: GitHub Actions, https://github.com/mirceaulinic/salt-sproxy/actions
Project-URL: Docs: RTD, https://salt-sproxy.readthedocs.io/
Project-URL: GitHub: issues, https://github.com/mirceaulinic/salt-sproxy/issues
Project-URL: GitHub: repo, https://github.com/mirceaulinic/salt-sproxy
Keywords: salt,network,automation,cli,proxy,minion,salt-extension
Classifier: Development Status :: 5 - Production/Stable
Classifier: Environment :: Console
Classifier: Environment :: Plugins
Classifier: License :: OSI Approved :: Apache Software License
Classifier: Topic :: Utilities
Classifier: Topic :: System :: Networking
Classifier: Topic :: System :: Clustering
Classifier: Topic :: System :: Operating System
Classifier: Topic :: System :: Distributed Computing
Classifier: Topic :: System :: Systems Administration
Classifier: Programming Language :: Python
Classifier: Programming Language :: Cython
Classifier: Programming Language :: Python :: 3 :: Only
Classifier: Programming Language :: Python :: 3.8
Classifier: Programming Language :: Python :: 3.9
Classifier: Programming Language :: Python :: 3.10
Classifier: Programming Language :: Python :: 3.11
Classifier: Programming Language :: Python :: 3.12
Classifier: Operating System :: POSIX
Classifier: Operating System :: Microsoft :: Windows
Classifier: Operating System :: MacOS
Classifier: Intended Audience :: Developers
Classifier: Intended Audience :: Telecommunications Industry
Classifier: Intended Audience :: System Administrators
Classifier: Intended Audience :: Education
Classifier: Intended Audience :: Science/Research
License-File: LICENSE
Requires-Dist: six
Requires-Dist: salt
Requires-Dist: progressbar2
Provides-Extra: api
Requires-Dist: cherrypy (>=18.8.0) ; extra == 'api'
Provides-Extra: junos
Requires-Dist: junos-eznc ; extra == 'junos'
Provides-Extra: napalm
Requires-Dist: napalm ; extra == 'napalm'
Provides-Extra: netbox
Requires-Dist: pynetbox ; extra == 'netbox'
Provides-Extra: netmiko
Requires-Dist: netmiko ; extra == 'netmiko'
